cratedb_mcp/__init__.py
cratedb_mcp/__main__.py
cratedb_mcp/cli.py
cratedb_mcp/knowledge.py
cratedb_mcp/settings.py
cratedb_mcp/util/__init__.py
cratedb_mcp/util/sql.py
mseep_cratedb_mcp-1.0.1.dist-info/licenses/LICENSE
mseep_cratedb_mcp-1.0.1.dist-info/METADATA
mseep_cratedb_mcp-1.0.1.dist-info/WHEEL
mseep_cratedb_mcp-1.0.1.dist-info/top_level.txt
mseep_cratedb_mcp-1.0.1.dist-info/RECORD
