Metadata-Version: 2.4
Name: mseep-cratedb-mcp
Version: 1.0.1
Summary: CrateDB MCP Server for natural-language Text-to-SQL and documentation retrieval.
Home-page: https://github.com/mseep
Author: mseep
Author-email: support@skydeck.ai
Maintainer: mseep
Maintainer-email: support@skydeck.ai
Keywords: mseep,cratedb,documentation retrieval,knowledge base,mcp,mcp server,model context protocol,sql,text-to-sql
Classifier: Programming Language :: Python :: 3
Classifier: License :: OSI Approved :: MIT License
Classifier: Operating System :: OS Independent
Requires-Python: >=3.6
License-File: LICENSE
Requires-Dist: attrs
Requires-Dist: cachetools<7
Requires-Dist: click<9
Requires-Dist: cratedb-about==0.0.5
Requires-Dist: fastmcp<2.7
Requires-Dist: hishel<0.2
Requires-Dist: pueblo==0.0.11
Requires-Dist: sqlparse<0.6
Dynamic: author
Dynamic: author-email
Dynamic: classifier
Dynamic: description
Dynamic: description-content-type
Dynamic: home-page
Dynamic: keywords
Dynamic: license-file
Dynamic: maintainer
Dynamic: maintainer-email
Dynamic: requires-dist
Dynamic: requires-python
Dynamic: summary
